csv_generator/__init__.py
csv_generator/admin.py
csv_generator/attribute_descriptors.py
csv_generator/forms.py
csv_generator/models.py
csv_generator/utils.py
csv_generator/views.py
csv_generator/migrations/0001_initial.py
csv_generator/migrations/__init__.py
csv_generator/templates/admin/csv_generator/csv_generator_select.html
csv_generator/tests/__init__.py
csv_generator/tests/factories.py
csv_generator/tests/models.py
csv_generator/tests/test_admin.py
csv_generator/tests/test_attribute_descriptors.py
csv_generator/tests/test_csv_generator_column_form.py
csv_generator/tests/test_csv_generator_column_model.py
csv_generator/tests/test_csv_generator_form.py
csv_generator/tests/test_csv_generator_formset.py
csv_generator/tests/test_csv_generator_model.py
csv_generator/tests/test_select_csv_generator_form.py
csv_generator/tests/test_views.py
csv_generator/tests/utils.py
csv_generator-1.0.2.dist-info/LICENSE
csv_generator-1.0.2.dist-info/METADATA
csv_generator-1.0.2.dist-info/WHEEL
csv_generator-1.0.2.dist-info/top_level.txt
csv_generator-1.0.2.dist-info/RECORD
