Metadata-Version: 2.1
Name: csv-generator
Version: 1.0.2
Summary: Configurable CSV Generator for Django
Home-page: https://github.com/fatboystring/csv_generator/
Author: Dan Stringer
Author-email: dan.stringer1983@googlemail.com
License: MIT
Download-URL: https://github.com/fatboystring/csv_generator/tarball/1.0.2
Keywords: csv generator,queryset,django
Platform: UNKNOWN
Classifier: Development Status :: 5 - Production/Stable
Classifier: Intended Audience :: Developers
Classifier: Topic :: Software Development :: Libraries :: Python Modules
Classifier: License :: OSI Approved :: MIT License
Classifier: Programming Language :: Python :: 2
Classifier: Programming Language :: Python :: 2.7
Classifier: Programming Language :: Python :: 3
Classifier: Programming Language :: Python :: 3.4
Classifier: Programming Language :: Python :: 3.5
Classifier: Programming Language :: Python :: 3.6
Classifier: Programming Language :: Python :: 3.7
Classifier: Programming Language :: Python :: 3.8
